LICENSE
MANIFEST.in
Makefile
README.rst
setup.cfg
setup.py
pretalx_hitalx/__init__.py
pretalx_hitalx/apps.py
pretalx_hitalx/form.py
pretalx_hitalx/models.py
pretalx_hitalx/signals.py
pretalx_hitalx/urls.py
pretalx_hitalx/views.py
pretalx_hitalx.egg-info/PKG-INFO
pretalx_hitalx.egg-info/SOURCES.txt
pretalx_hitalx.egg-info/dependency_links.txt
pretalx_hitalx.egg-info/entry_points.txt
pretalx_hitalx.egg-info/requires.txt
pretalx_hitalx.egg-info/top_level.txt
pretalx_hitalx/locale/de_DE/LC_MESSAGES/.gitkeep
pretalx_hitalx/locale/de_DE/LC_MESSAGES/django.mo
pretalx_hitalx/locale/de_DE/LC_MESSAGES/django.po
pretalx_hitalx/locale/fr_FR/LC_MESSAGES/.gitkeep
pretalx_hitalx/migrations/0001_initial.py
pretalx_hitalx/migrations/0002_auto_20220427_0849.py
pretalx_hitalx/migrations/0003_tour.py
pretalx_hitalx/migrations/__init__.py
pretalx_hitalx/static/pretalx_hitalx/.gitkeep
pretalx_hitalx/templates/pretalx_hitalx/.gitkeep
pretalx_hitalx/templates/pretalx_hitalx/speaker_expense.html
pretalx_hitalx/templates/pretalx_hitalx/speaker_expenses.html
pretalx_hitalx/templates/pretalx_hitalx/speaker_tours.html
pretalx_hitalx/templates/pretalx_hitalx/speakers.html
pretalx_hitalx/templates/pretalx_hitalx/tour.html
pretalx_hitalx/templates/pretalx_hitalx/tour_confirm_delete.html
pretalx_hitalx/templates/pretalx_hitalx/tours.html
pretalx_hitalx/templates/pretalx_hitalx/tours_export.html
pretalx_hitalx/templatetags/__init__.py
pretalx_hitalx/templatetags/pretalx_hitalx.py