Metadata-Version: 2.1
Name: pretalx-hitalx
Version: 0.0.11
Summary: Some utilities specifically for the Hedonist International
Home-page: https://github.com/l0rn/pretalx-hitlax
Author: Jonatan Zint
Author-email: j.zint@frykk.de
License: Apache Software License
Platform: UNKNOWN
License-File: LICENSE
